acto/__init__.py
acto/email.py
acto/log.py
acto/monitor.py
acto/periods.py
acto/retry.py
acto/tests.py
acto/times.py
acto-0.6.3.dist-info/licenses/LICENSE
acto-0.6.3.dist-info/METADATA
acto-0.6.3.dist-info/WHEEL
acto-0.6.3.dist-info/top_level.txt
acto-0.6.3.dist-info/RECORD
