Metadata-Version: 2.4
Name: acto
Version: 0.6.3
Summary: Automate Common Tasks On-demand
Author: Hansimov
Project-URL: Homepage, https://github.com/Hansimov/acto
Project-URL: Issues, https://github.com/Hansimov/acto/issues
Classifier: Programming Language :: Python :: 3
Classifier: License :: OSI Approved :: MIT License
Classifier: Operating System :: OS Independent
Requires-Python: >=3.6
License-File: LICENSE
Requires-Dist: tclogger
Dynamic: license-file
